{
  "appPageId" : "a01d02bb-e968-4c73-b167-df75dbb54a39",
  "componentName" : "siteforce:sldsOneColLayout",
  "id" : "912f2f39-5315-4728-a8e4-4d192da091d4",
  "label" : "Flow",
  "regions" : [ {
    "id" : "aeb18390-5750-438e-a942-700c557eb3fd",
    "regionName" : "header",
    "type" : "region"
  }, {
    "components" : [ {
      "componentAttributes" : {
        "flowArguments" : "",
        "flowLayout" : "oneColumn",
        "flowName" : "{!flowName}"
      },
      "componentName" : "forceCommunity:flowCommunity",
      "id" : "6c42139d-d2e5-46b7-be30-9c3526907656",
      "renderPriority" : "NEUTRAL",
      "renditionMap" : { },
      "type" : "component"
    } ],
    "id" : "9d7cb51f-09ee-48c2-a3f5-c0d27ee44e73",
    "regionName" : "content",
    "type" : "region"
  }, {
    "id" : "644ebcee-0834-4f40-8b01-c824922fde46",
    "regionName" : "footer",
    "type" : "region"
  } ],
  "themeLayoutType" : "Inner",
  "type" : "view",
  "viewType" : "flow"
}