{
  "appPageId" : "6a9b6d80-00b0-4cef-8aa2-5c894fa6cbfd",
  "componentName" : "siteforce:sldsOneColLayout",
  "id" : "f06a8b5f-31b8-4fe6-af64-54f160836e81",
  "label" : "Record Detail",
  "regions" : [ {
    "components" : [ {
      "componentAttributes" : {
        "bannerText" : "TESTTESTTTT",
        "bannerTextWithKnowledge" : "Explore other <a href=\"javascript:void(0)\" class=\"headlineArticles\">articles</a> and <a href=\"javascript:void(0)\" class=\"headlineDiscussions\">discussions</a> on this topic.",
        "bannerTextWithoutKnowledge" : "Explore other <a href=\"javascript:void(0)\" class=\"headlineDiscussions\">discussions</a> on this topic.",
        "pageType" : "",
        "showSubTopics" : true,
        "title" : "TEST TEST",
        "uniqueNameOrId" : ""
      },
      "componentName" : "forceCommunity:headline",
      "id" : "b32f57a2-0b2a-4283-892e-2b03a4373740",
      "renderPriority" : "NEUTRAL",
      "renditionMap" : { },
      "type" : "component"
    } ],
    "id" : "787499e1-d0c3-4ca8-92e5-872398e835aa",
    "regionName" : "header",
    "type" : "region"
  }, {
    "components" : [ {
      "componentAttributes" : {
        "recordId" : "{!recordId}"
      },
      "componentName" : "forceCommunity:recordHeadline",
      "id" : "0d773e4c-f9f6-4018-a7b4-e81319736c03",
      "renderPriority" : "NEUTRAL",
      "renditionMap" : { },
      "type" : "component"
    }, {
      "componentAttributes" : {
        "detailsTabLabel" : "Details",
        "discussionsTabLabel" : "Feed",
        "recordId" : "{!recordId}",
        "relatedTabLabel" : "Related",
        "tab1Type" : "details",
        "tab2Type" : "related",
        "tab3Type" : "chatter",
        "tab4Type" : "none",
        "timelineTabLabel" : "Activity"
      },
      "componentName" : "forceCommunity:recordHomeTabs",
      "id" : "b0557fca-ea4d-44af-a9f8-cf1467451f7d",
      "renderPriority" : "NEUTRAL",
      "renditionMap" : { },
      "type" : "component"
    } ],
    "id" : "319040a0-6a7b-44ff-8f3a-302624935044",
    "regionName" : "content",
    "type" : "region"
  }, {
    "id" : "14ad6631-c31d-4827-801c-695c35cb8595",
    "regionName" : "footer",
    "type" : "region"
  }, {
    "components" : [ {
      "componentAttributes" : {
        "customHeadTags" : "",
        "description" : "",
        "title" : "{!Record._Object}: {!Record._Title}"
      },
      "componentName" : "forceCommunity:seoAssistant",
      "id" : "54dcf2d1-df24-4144-87c7-dd8b4e5c99c2",
      "renditionMap" : { },
      "type" : "component"
    } ],
    "id" : "413493fe-5b1c-4b08-8bdc-1457b66bbf5d",
    "regionName" : "sfdcHiddenRegion",
    "type" : "region"
  } ],
  "themeLayoutType" : "Inner",
  "type" : "view",
  "viewType" : "detail"
}